enthusiast_source_shopware/__init__.py
enthusiast_source_shopware/source.py
enthusiast_source_shopware-1.2.0.dist-info/METADATA
enthusiast_source_shopware-1.2.0.dist-info/WHEEL
enthusiast_source_shopware-1.2.0.dist-info/RECORD
